clean_migrations/__init__.py
clean_migrations/main.py
clean_migrations-1.0.2.dist-info/METADATA
clean_migrations-1.0.2.dist-info/WHEEL
clean_migrations-1.0.2.dist-info/entry_points.txt
clean_migrations-1.0.2.dist-info/top_level.txt
clean_migrations-1.0.2.dist-info/RECORD
