Metadata-Version: 2.1
Name: clean_migrations
Version: 1.0.2
Summary: Herramienta para limpiar migraciones en proyectos Django
Home-page: https://github.com/h4cker54n/clean_migrations
Author: H4cker54n
Author-email: snbq89@gmail.com
Classifier: Programming Language :: Python :: 3
Classifier: License :: OSI Approved :: MIT License
Classifier: Operating System :: OS Independent
Classifier: Framework :: Django
Requires-Python: >=3.6
